marearts_crystal/__init__.py
marearts_crystal/ma_crystal.cpython-311-aarch64-linux-gnu.so
marearts_crystal-2.4.2.dist-info/licenses/LICENSE
marearts_crystal-2.4.2.dist-info/METADATA
marearts_crystal-2.4.2.dist-info/WHEEL
marearts_crystal-2.4.2.dist-info/top_level.txt
marearts_crystal-2.4.2.dist-info/RECORD
