Metadata-Version: 2.1
Name: marearts-crystal
Version: 2.4.2
Summary: marearts crystal for encryption and decryption
Home-page: https://www.marearts.com
Author: MareArts
Author-email: MareArts <hello@marearts.com>
License: MIT
Classifier: Programming Language :: Python :: 3.9
Classifier: Programming Language :: Python :: 3.10
Classifier: Programming Language :: Python :: 3.11
Classifier: Programming Language :: Python :: 3.12
Classifier: Operating System :: OS Independent
Requires-Python: <3.13,>=3.9
License-File: LICENSE
Requires-Dist: cffi==1.16.0
Requires-Dist: cryptography==43.0.0
Requires-Dist: pycparser==2.22
